landscaper/__init__.py
landscaper/compute.py
landscaper/hessian.py
landscaper/landscape.py
landscaper/plots.py
landscaper/tda.py
landscaper/topology_profile.py
landscaper/utils.py
landscaper-1.3.1.dist-info/licenses/LICENSE
landscaper-1.3.1.dist-info/METADATA
landscaper-1.3.1.dist-info/WHEEL
landscaper-1.3.1.dist-info/top_level.txt
landscaper-1.3.1.dist-info/RECORD
