Metadata-Version: 2.4
Name: Landscaper
Version: 1.3.1
Summary: A comprehensive Python framework designed for exploring the loss landscapes of deep learning models.
Author-email: Jiaqing Chen <jchen501@asu.edu>, Nicholas Hadler <nhadler@berkeley.edu>, Tiankai Xie <txie21@asu.edu>, Rostyslav Hnatyshyn <rhnatysh@asu.edu>
License-Expression: BSD-3-Clause-LBNL
Project-URL: Homepage, https://github.com/Vis4SciML/Landscaper
Project-URL: Documentation, https://vis4sciml.github.io/Landscaper/
Project-URL: Repository, https://github.com/Vis4SciML/Landscaper
Project-URL: Issues, https://github.com/Vis4SciML/Landscaper/issues
Requires-Python: <3.13,>=3.10.0
License-File: LICENSE
Requires-Dist: gudhi>=3.11.0
Requires-Dist: matplotlib>=3.10.1
Requires-Dist: pandas>=2.2.3
Requires-Dist: topopy>=1.0.4
Requires-Dist: treelib>=1.7.1
Requires-Dist: coloraide>=4.6
Requires-Dist: tqdm>=4.67.1
Requires-Dist: drawsvg>=2.4.0
Provides-Extra: docs
Requires-Dist: jupyter>=1.1.1; extra == "docs"
Requires-Dist: mkdocs-gen-files>=0.5.0; extra == "docs"
Requires-Dist: mkdocs-jupyter>=0.25.1; extra == "docs"
Requires-Dist: mkdocs-literate-nav>=0.6.2; extra == "docs"
Requires-Dist: mkdocs-material>=9.6.14; extra == "docs"
Requires-Dist: mkdocs-section-index>=0.3.10; extra == "docs"
Requires-Dist: mkdocstrings[python]>=0.29.1; extra == "docs"
Provides-Extra: examples
Requires-Dist: torch>=2.7.0; extra == "examples"
Requires-Dist: torch-geometric>=2.6.1; extra == "examples"
Requires-Dist: torchvision>=0.22.0; extra == "examples"
Dynamic: license-file
